handmadeML/__init__.py
handmadeML/common/utils.py
handmadeML/data/.keep
handmadeML/decisiontrees/__init__.py
handmadeML/decisiontrees/models.py
handmadeML/decisiontrees/utils.py
handmadeML/linearmodels/__init__.py
handmadeML/linearmodels/models.py
handmadeML/linearmodels/utils.py
handmadeML/metamethods/__init__.py
handmadeML/metamethods/ensemble.py
handmadeML/neuralnets/__init__.py
handmadeML/neuralnets/models.py
handmadeML/neuralnets/utils.py
handmadeML/optimizers/__init__.py
handmadeML/optimizers/adam.py
handmadeML-1.1.data/scripts/handmadeML-run
tests/__init__.py
tests/common/test_common_utils.py
tests/decisiontrees/test_decisiontrees_models.py
tests/linearmodels/test_linearmodels_models.py
tests/neuralnets/test_neuralnets_models.py
tests/neuralnets/test_neuralnets_utils.py
tests/optimizers/test_optimizers.py
handmadeML-1.1.dist-info/LICENCE
handmadeML-1.1.dist-info/METADATA
handmadeML-1.1.dist-info/WHEEL
handmadeML-1.1.dist-info/top_level.txt
handmadeML-1.1.dist-info/RECORD
