Metadata-Version: 2.1
Name: handmadeML
Version: 1.1
Summary: 'Personal machine/deep learning implementation inspired by sklearn and keras'
Home-page: https://github.com/bdepebhe/handmadeML
Author: Thomas Mathieu
Author-email: thomas.mathieu@m4x.org
License: UNKNOWN
Platform: UNKNOWN
Classifier: Programming Language :: Python :: 3
Classifier: License :: OSI Approved :: MIT License
Classifier: Operating System :: OS Independent
Requires-Python: >=3.6
Requires-Dist: pip (>=9)
Requires-Dist: setuptools (>=26)
Requires-Dist: twine
Requires-Dist: wheel (>=0.29)
Requires-Dist: matplotlib
Requires-Dist: numpy
Requires-Dist: pandas
Requires-Dist: scikit-learn
Requires-Dist: black
Requires-Dist: coverage
Requires-Dist: pytest
Requires-Dist: seaborn
